setup.cfg
setup.py
bin/peppa
peppa/__init__.py
peppa.egg-info/PKG-INFO
peppa.egg-info/SOURCES.txt
peppa.egg-info/dependency_links.txt
peppa.egg-info/pbr.json
peppa.egg-info/requires.txt
peppa.egg-info/top_level.txt