Metadata-Version: 1.0
Name: peppa
Version: 0.1
Summary: A CLI front-end to a running salt-api system
Home-page: https://github.com/iamseth/peppa
Author: Seth Miller
Author-email: seth@sethmiller.me
License: UNKNOWN
Platform: UNKNOWN
